<powerpagecomponent powerpagecomponentid="67befd13-869a-4907-91e8-43f66296d24d">
  <content>{
  "description": "This is the default studio template. Please do not modify.",
  "type": 756150001,
  "usewebsiteheaderandfooter": true,
  "webtemplateid": "a1e79364-0dc0-4035-82f7-99ee84523007",
  "isdefault": false
}</content>
  <iscustomizable>1</iscustomizable>
  <name>AI Search PageTemplate</name>
  <powerpagecomponenttype>6</powerpagecomponenttype>
  <powerpagesiteid>
    <powerpagesiteid>6bd7e950-b198-4aca-9d6c-989af327a096</powerpagesiteid>
  </powerpagesiteid>
  <statecode>0</statecode>
  <statuscode>1</statuscode>
</powerpagecomponent>